[
    {
        "Description": "{{PageRef|}}*{{PageRef|}} {{PageRef|}}{{{PageRef|}}{{{PageRef|}}P{{PageRef|}}a{{PageRef|}}g{{PageRef|}}e{{PageRef|}}R{{PageRef|}}e{{PageRef|}}f{{PageRef|}}|{{PageRef|}}S{{PageRef|}}p{{PageRef|}}i{{PageRef|}}r{{PageRef|}}i{{PageRef|}}t{{PageRef|}} {{PageRef|}}S{{PageRef|}}t{{PageRef|}}r{{PageRef|}}i{{PageRef|}}k{{PageRef|}}e{{PageRef|}}}{{PageRef|}}}{{PageRef|}}:{{PageRef|}} {{PageRef|}}M{{PageRef|}}e{{PageRef|}}l{{PageRef|}}e{{PageRef|}}e{{PageRef|}} {{PageRef|}}d{{PageRef|}}a{{PageRef|}}m{{PageRef|}}a{{PageRef|}}g{{PageRef|}}e{{PageRef|}} {{PageRef|}}r{{PageRef|}}e{{PageRef|}}d{{PageRef|}}u{{PageRef|}}c{{PageRef|}}e{{PageRef|}}d{{PageRef|}} {{PageRef|}}f{{PageRef|}}r{{PageRef|}}o{{PageRef|}}m{{PageRef|}} {{PageRef|}}2{{PageRef|}}0{{PageRef|}}%{{PageRef|}} {{PageRef|}}t{{PageRef|}}o{{PageRef|}} {{PageRef|}}1{{PageRef|}}5{{PageRef|}}%{{PageRef|}}",
        "Tags": [
            "Spirit Strike",
            "Item",
            "Spirit Item",
            "",
            "Hero",
            "Ability",
            "Melee"
        ]
    },
    {
        "Description": "{{PageRef|}}*{{PageRef|}} {{PageRef|}}{{{PageRef|}}{{{PageRef|}}P{{PageRef|}}a{{PageRef|}}g{{PageRef|}}e{{PageRef|}}R{{PageRef|}}e{{PageRef|}}f{{PageRef|}}|{{PageRef|}}M{{PageRef|}}e{{PageRef|}}l{{PageRef|}}e{{PageRef|}}e{{PageRef|}} {{PageRef|}}C{{PageRef|}}h{{PageRef|}}a{{PageRef|}}r{{PageRef|}}g{{PageRef|}}e{{PageRef|}}}{{PageRef|}}}{{PageRef|}}:{{PageRef|}} {{PageRef|}}N{{PageRef|}}o{{PageRef|}} {{PageRef|}}l{{PageRef|}}o{{PageRef|}}n{{PageRef|}}g{{PageRef|}}e{{PageRef|}}r{{PageRef|}} {{PageRef|}}g{{PageRef|}}r{{PageRef|}}a{{PageRef|}}n{{PageRef|}}t{{PageRef|}}s{{PageRef|}} {{PageRef|}}+{{PageRef|}}1{{PageRef|}}5{{PageRef|}}%{{PageRef|}} {{PageRef|}}M{{PageRef|}}e{{PageRef|}}l{{PageRef|}}e{{PageRef|}}e{{PageRef|}} {{PageRef|}}D{{PageRef|}}a{{PageRef|}}m{{PageRef|}}a{{PageRef|}}g{{PageRef|}}e{{PageRef|}}",
        "Tags": [
            "Melee Charge",
            "Item",
            "Weapon Item",
            "",
            "Hero",
            "Ability",
            "Melee"
        ]
    },
    {
        "Description": "{{PageRef|}}*{{PageRef|}} {{PageRef|}}{{{PageRef|}}{{{PageRef|}}P{{PageRef|}}a{{PageRef|}}g{{PageRef|}}e{{PageRef|}}R{{PageRef|}}e{{PageRef|}}f{{PageRef|}}|{{PageRef|}}V{{PageRef|}}e{{PageRef|}}i{{PageRef|}}l{{PageRef|}} {{PageRef|}}W{{PageRef|}}a{{PageRef|}}l{{PageRef|}}k{{PageRef|}}e{{PageRef|}}r{{PageRef|}}}{{PageRef|}}}{{PageRef|}}:{{PageRef|}} {{PageRef|}}B{{PageRef|}}u{{PageRef|}}l{{PageRef|}}l{{PageRef|}}e{{PageRef|}}t{{PageRef|}} {{PageRef|}}S{{PageRef|}}h{{PageRef|}}i{{PageRef|}}e{{PageRef|}}l{{PageRef|}}d{{PageRef|}} {{PageRef|}}r{{PageRef|}}e{{PageRef|}}d{{PageRef|}}u{{PageRef|}}c{{PageRef|}}e{{PageRef|}}d{{PageRef|}} {{PageRef|}}f{{PageRef|}}r{{PageRef|}}o{{PageRef|}}m{{PageRef|}} {{PageRef|}}+{{PageRef|}}2{{PageRef|}}0{{PageRef|}}0{{PageRef|}} {{PageRef|}}t{{PageRef|}}o{{PageRef|}} {{PageRef|}}+{{PageRef|}}1{{PageRef|}}5{{PageRef|}}0{{PageRef|}}",
        "Tags": [
            "Veil Walker",
            "Item",
            "Vitality Item",
            "",
            "Hero",
            "Ability",
            "Objective",
            "Walker",
            "Cosmic Veil"
        ]
    },
    {
        "Description": "{{PageRef|}}*{{PageRef|}} {{PageRef|}}{{{PageRef|}}{{{PageRef|}}P{{PageRef|}}a{{PageRef|}}g{{PageRef|}}e{{PageRef|}}R{{PageRef|}}e{{PageRef|}}f{{PageRef|}}|{{PageRef|}}V{{PageRef|}}e{{PageRef|}}i{{PageRef|}}l{{PageRef|}} {{PageRef|}}W{{PageRef|}}a{{PageRef|}}l{{PageRef|}}k{{PageRef|}}e{{PageRef|}}r{{PageRef|}}}{{PageRef|}}}{{PageRef|}}:{{PageRef|}} {{PageRef|}}S{{PageRef|}}h{{PageRef|}}i{{PageRef|}}e{{PageRef|}}l{{PageRef|}}d{{PageRef|}} {{PageRef|}}r{{PageRef|}}e{{PageRef|}}s{{PageRef|}}t{{PageRef|}}o{{PageRef|}}r{{PageRef|}}e{{PageRef|}} {{PageRef|}}n{{PageRef|}}o{{PageRef|}}w{{PageRef|}} {{PageRef|}}t{{PageRef|}}a{{PageRef|}}k{{PageRef|}}e{{PageRef|}}s{{PageRef|}} {{PageRef|}}5{{PageRef|}}s{{PageRef|}} {{PageRef|}}t{{PageRef|}}o{{PageRef|}} {{PageRef|}}f{{PageRef|}}u{{PageRef|}}l{{PageRef|}}l{{PageRef|}}y{{PageRef|}} {{PageRef|}}r{{PageRef|}}e{{PageRef|}}g{{PageRef|}}e{{PageRef|}}n{{PageRef|}}",
        "Tags": [
            "Veil Walker",
            "Item",
            "Vitality Item",
            "",
            "Hero",
            "Ability",
            "Objective",
            "Walker",
            "Cosmic Veil"
        ]
    },
    {
        "Description": "{{PageRef|}}*{{PageRef|}} {{PageRef|}}{{{PageRef|}}{{{PageRef|}}P{{PageRef|}}a{{PageRef|}}g{{PageRef|}}e{{PageRef|}}R{{PageRef|}}e{{PageRef|}}f{{PageRef|}}|{{PageRef|}}V{{PageRef|}}e{{PageRef|}}i{{PageRef|}}l{{PageRef|}} {{PageRef|}}W{{PageRef|}}a{{PageRef|}}l{{PageRef|}}k{{PageRef|}}e{{PageRef|}}r{{PageRef|}}}{{PageRef|}}}{{PageRef|}}:{{PageRef|}} {{PageRef|}}C{{PageRef|}}o{{PageRef|}}o{{PageRef|}}l{{PageRef|}}d{{PageRef|}}o{{PageRef|}}w{{PageRef|}}n{{PageRef|}} {{PageRef|}}i{{PageRef|}}n{{PageRef|}}c{{PageRef|}}r{{PageRef|}}e{{PageRef|}}a{{PageRef|}}s{{PageRef|}}e{{PageRef|}}d{{PageRef|}} {{PageRef|}}f{{PageRef|}}r{{PageRef|}}o{{PageRef|}}m{{PageRef|}} {{PageRef|}}2{{PageRef|}}0{{PageRef|}}s{{PageRef|}} {{PageRef|}}t{{PageRef|}}o{{PageRef|}} {{PageRef|}}2{{PageRef|}}5{{PageRef|}}s{{PageRef|}}",
        "Tags": [
            "Veil Walker",
            "Item",
            "Vitality Item",
            "",
            "Hero",
            "Ability",
            "Objective",
            "Walker",
            "Cosmic Veil"
        ]
    },
    {
        "Description": "{{PageRef|}}*{{PageRef|}} {{PageRef|}}{{{PageRef|}}{{{PageRef|}}P{{PageRef|}}a{{PageRef|}}g{{PageRef|}}e{{PageRef|}}R{{PageRef|}}e{{PageRef|}}f{{PageRef|}}|{{PageRef|}}Y{{PageRef|}}a{{PageRef|}}m{{PageRef|}}a{{PageRef|}}t{{PageRef|}}o{{PageRef|}}}{{PageRef|}}}{{PageRef|}}:{{PageRef|}} {{PageRef|}}{{{PageRef|}}{{{PageRef|}}P{{PageRef|}}a{{PageRef|}}g{{PageRef|}}e{{PageRef|}}R{{PageRef|}}e{{PageRef|}}f{{PageRef|}}|{{PageRef|}}S{{PageRef|}}h{{PageRef|}}a{{PageRef|}}d{{PageRef|}}o{{PageRef|}}w{{PageRef|}} {{PageRef|}}T{{PageRef|}}r{{PageRef|}}a{{PageRef|}}n{{PageRef|}}s{{PageRef|}}f{{PageRef|}}o{{PageRef|}}r{{PageRef|}}m{{PageRef|}}a{{PageRef|}}t{{PageRef|}}i{{PageRef|}}o{{PageRef|}}n{{PageRef|}}}{{PageRef|}}}{{PageRef|}} {{PageRef|}}n{{PageRef|}}o{{PageRef|}}w{{PageRef|}} {{PageRef|}}c{{PageRef|}}a{{PageRef|}}u{{PageRef|}}s{{PageRef|}}e{{PageRef|}}s{{PageRef|}} {{PageRef|}}y{{PageRef|}}o{{PageRef|}}u{{PageRef|}} {{PageRef|}}t{{PageRef|}}o{{PageRef|}} {{PageRef|}}b{{PageRef|}}e{{PageRef|}} {{PageRef|}}u{{PageRef|}}n{{PageRef|}}a{{PageRef|}}b{{PageRef|}}l{{PageRef|}}e{{PageRef|}} {{PageRef|}}t{{PageRef|}}o{{PageRef|}} {{PageRef|}}d{{PageRef|}}i{{PageRef|}}e{{PageRef|}} {{PageRef|}}d{{PageRef|}}u{{PageRef|}}r{{PageRef|}}i{{PageRef|}}n{{PageRef|}}g{{PageRef|}} {{PageRef|}}t{{PageRef|}}h{{PageRef|}}e{{PageRef|}} {{PageRef|}}b{{PageRef|}}u{{PageRef|}}f{{PageRef|}}f{{PageRef|}}",
        "Tags": [
            "Shadow Transformation",
            "Hero",
            "Ability",
            "Yamato",
            ""
        ]
    },
    {
        "Description": "{{PageRef|}}*{{PageRef|}} {{PageRef|}}T{{PageRef|}}h{{PageRef|}}e{{PageRef|}}r{{PageRef|}}e{{PageRef|}} {{PageRef|}}i{{PageRef|}}s{{PageRef|}} {{PageRef|}}n{{PageRef|}}o{{PageRef|}} {{PageRef|}}l{{PageRef|}}o{{PageRef|}}n{{PageRef|}}g{{PageRef|}}e{{PageRef|}}r{{PageRef|}} {{PageRef|}}a{{PageRef|}} {{PageRef|}}r{{PageRef|}}e{{PageRef|}}i{{PageRef|}}n{{PageRef|}}f{{PageRef|}}o{{PageRef|}}r{{PageRef|}}c{{PageRef|}}e{{PageRef|}}m{{PageRef|}}e{{PageRef|}}n{{PageRef|}}t{{PageRef|}} {{PageRef|}}t{{PageRef|}}r{{PageRef|}}o{{PageRef|}}o{{PageRef|}}p{{PageRef|}}e{{PageRef|}}r{{PageRef|}} {{PageRef|}}w{{PageRef|}}a{{PageRef|}}v{{PageRef|}}e{{PageRef|}} {{PageRef|}}a{{PageRef|}}f{{PageRef|}}t{{PageRef|}}e{{PageRef|}}r{{PageRef|}} {{PageRef|}}G{{PageRef|}}u{{PageRef|}}a{{PageRef|}}r{{PageRef|}}d{{PageRef|}}i{{PageRef|}}a{{PageRef|}}n{{PageRef|}}s{{PageRef|}} {{PageRef|}}a{{PageRef|}}n{{PageRef|}}d{{PageRef|}} {{PageRef|}}W{{PageRef|}}a{{PageRef|}}l{{PageRef|}}k{{PageRef|}}e{{PageRef|}}r{{PageRef|}}s{{PageRef|}} {{PageRef|}}d{{PageRef|}}i{{PageRef|}}e{{PageRef|}}",
        "Tags": [
            "",
            "Hero",
            "Ability",
            "Objective",
            "Guardian",
            "Walker"
        ]
    }
]