[
    {
        "Description": "{{PageRef|}}*{{PageRef|}} {{PageRef|}}O{{PageRef|}}u{{PageRef|}}t{{PageRef|}}e{{PageRef|}}r{{PageRef|}} {{PageRef|}}z{{PageRef|}}i{{PageRef|}}p{{PageRef|}}l{{PageRef|}}i{{PageRef|}}n{{PageRef|}}e{{PageRef|}}s{{PageRef|}} {{PageRef|}}h{{PageRef|}}e{{PageRef|}}r{{PageRef|}}o{{PageRef|}} {{PageRef|}}s{{PageRef|}}p{{PageRef|}}e{{PageRef|}}e{{PageRef|}}d{{PageRef|}} {{PageRef|}}i{{PageRef|}}n{{PageRef|}}c{{PageRef|}}r{{PageRef|}}e{{PageRef|}}a{{PageRef|}}s{{PageRef|}}e{{PageRef|}}d{{PageRef|}} {{PageRef|}}b{{PageRef|}}y{{PageRef|}} {{PageRef|}}2{{PageRef|}}0{{PageRef|}}%{{PageRef|}} {{PageRef|}}r{{PageRef|}}e{{PageRef|}}l{{PageRef|}}a{{PageRef|}}t{{PageRef|}}i{{PageRef|}}v{{PageRef|}}e{{PageRef|}} {{PageRef|}}t{{PageRef|}}o{{PageRef|}} {{PageRef|}}i{{PageRef|}}n{{PageRef|}}n{{PageRef|}}e{{PageRef|}}r{{PageRef|}} {{PageRef|}}l{{PageRef|}}a{{PageRef|}}n{{PageRef|}}e{{PageRef|}}s{{PageRef|}} {{PageRef|}}({{PageRef|}}s{{PageRef|}}a{{PageRef|}}m{{PageRef|}}e{{PageRef|}} {{PageRef|}}a{{PageRef|}}s{{PageRef|}} {{PageRef|}}t{{PageRef|}}r{{PageRef|}}o{{PageRef|}}o{{PageRef|}}p{{PageRef|}}e{{PageRef|}}r{{PageRef|}}s{{PageRef|}} {{PageRef|}}o{{PageRef|}}n{{PageRef|}} {{PageRef|}}o{{PageRef|}}u{{PageRef|}}t{{PageRef|}}e{{PageRef|}}r{{PageRef|}} {{PageRef|}}l{{PageRef|}}a{{PageRef|}}n{{PageRef|}}e{{PageRef|}}s{{PageRef|}} {{PageRef|}}z{{PageRef|}}i{{PageRef|}}p{{PageRef|}}l{{PageRef|}}i{{PageRef|}}n{{PageRef|}}e{{PageRef|}} {{PageRef|}}b{{PageRef|}}e{{PageRef|}}i{{PageRef|}}n{{PageRef|}}g{{PageRef|}} {{PageRef|}}f{{PageRef|}}a{{PageRef|}}s{{PageRef|}}t{{PageRef|}}e{{PageRef|}}r{{PageRef|}}){{PageRef|}}",
        "Tags": [
            "",
            "Hero",
            "Ability",
            "Zipline"
        ]
    },
    {
        "Description": "{{PageRef|}}*{{PageRef|}} {{PageRef|}}I{{PageRef|}}n{{PageRef|}}i{{PageRef|}}t{{PageRef|}}i{{PageRef|}}a{{PageRef|}}l{{PageRef|}} {{PageRef|}}r{{PageRef|}}e{{PageRef|}}s{{PageRef|}}p{{PageRef|}}a{{PageRef|}}w{{PageRef|}}n{{PageRef|}} {{PageRef|}}r{{PageRef|}}e{{PageRef|}}d{{PageRef|}}u{{PageRef|}}c{{PageRef|}}e{{PageRef|}}d{{PageRef|}} {{PageRef|}}f{{PageRef|}}r{{PageRef|}}o{{PageRef|}}m{{PageRef|}} {{PageRef|}}1{{PageRef|}}2{{PageRef|}}s{{PageRef|}} {{PageRef|}}t{{PageRef|}}o{{PageRef|}} {{PageRef|}}8{{PageRef|}}s{{PageRef|}}",
        "Tags": [
            "",
            "Hero",
            "Ability"
        ]
    },
    {
        "Description": "{{PageRef|}}*{{PageRef|}} {{PageRef|}}U{{PageRef|}}r{{PageRef|}}n{{PageRef|}} {{PageRef|}}n{{PageRef|}}o{{PageRef|}}w{{PageRef|}} {{PageRef|}}d{{PageRef|}}r{{PageRef|}}o{{PageRef|}}p{{PageRef|}}s{{PageRef|}} {{PageRef|}}w{{PageRef|}}h{{PageRef|}}e{{PageRef|}}n{{PageRef|}} {{PageRef|}}t{{PageRef|}}e{{PageRef|}}l{{PageRef|}}e{{PageRef|}}p{{PageRef|}}o{{PageRef|}}r{{PageRef|}}t{{PageRef|}}i{{PageRef|}}n{{PageRef|}}g{{PageRef|}} {{PageRef|}}w{{PageRef|}}i{{PageRef|}}t{{PageRef|}}h{{PageRef|}} {{PageRef|}}{{{PageRef|}}{{{PageRef|}}P{{PageRef|}}a{{PageRef|}}g{{PageRef|}}e{{PageRef|}}R{{PageRef|}}e{{PageRef|}}f{{PageRef|}}|{{PageRef|}}M{{PageRef|}}i{{PageRef|}}r{{PageRef|}}a{{PageRef|}}g{{PageRef|}}e{{PageRef|}}}{{PageRef|}}}{{PageRef|}}'{{PageRef|}}s{{PageRef|}} {{PageRef|}}{{{PageRef|}}{{{PageRef|}}P{{PageRef|}}a{{PageRef|}}g{{PageRef|}}e{{PageRef|}}R{{PageRef|}}e{{PageRef|}}f{{PageRef|}}|{{PageRef|}}T{{PageRef|}}r{{PageRef|}}a{{PageRef|}}v{{PageRef|}}e{{PageRef|}}l{{PageRef|}}e{{PageRef|}}r{{PageRef|}}}{{PageRef|}}}{{PageRef|}}",
        "Tags": [
            "Traveler",
            "Hero",
            "Ability",
            "Mirage",
            "",
            "Souls",
            "Soul Urn"
        ]
    },
    {
        "Description": "{{PageRef|}}*{{PageRef|}} {{PageRef|}}F{{PageRef|}}i{{PageRef|}}x{{PageRef|}}e{{PageRef|}}d{{PageRef|}} {{PageRef|}}{{{PageRef|}}{{{PageRef|}}P{{PageRef|}}a{{PageRef|}}g{{PageRef|}}e{{PageRef|}}R{{PageRef|}}e{{PageRef|}}f{{PageRef|}}|{{PageRef|}}W{{PageRef|}}r{{PageRef|}}a{{PageRef|}}i{{PageRef|}}t{{PageRef|}}h{{PageRef|}}}{{PageRef|}}}{{PageRef|}} {{PageRef|}}C{{PageRef|}}a{{PageRef|}}r{{PageRef|}}d{{PageRef|}}s{{PageRef|}},{{PageRef|}} {{PageRef|}}{{{PageRef|}}{{{PageRef|}}P{{PageRef|}}a{{PageRef|}}g{{PageRef|}}e{{PageRef|}}R{{PageRef|}}e{{PageRef|}}f{{PageRef|}}|{{PageRef|}}S{{PageRef|}}h{{PageRef|}}i{{PageRef|}}v{{PageRef|}}}{{PageRef|}}}{{PageRef|}} {{PageRef|}}R{{PageRef|}}a{{PageRef|}}g{{PageRef|}}e{{PageRef|}} {{PageRef|}}a{{PageRef|}}n{{PageRef|}}d{{PageRef|}} {{PageRef|}}l{{PageRef|}}i{{PageRef|}}f{{PageRef|}}e{{PageRef|}}s{{PageRef|}}t{{PageRef|}}e{{PageRef|}}a{{PageRef|}}l{{PageRef|}} {{PageRef|}}f{{PageRef|}}r{{PageRef|}}o{{PageRef|}}m{{PageRef|}} {{PageRef|}}i{{PageRef|}}n{{PageRef|}}c{{PageRef|}}r{{PageRef|}}e{{PageRef|}}a{{PageRef|}}s{{PageRef|}}i{{PageRef|}}n{{PageRef|}}g{{PageRef|}} {{PageRef|}}b{{PageRef|}}y{{PageRef|}} {{PageRef|}}s{{PageRef|}}h{{PageRef|}}o{{PageRef|}}o{{PageRef|}}t{{PageRef|}}i{{PageRef|}}n{{PageRef|}}g{{PageRef|}} {{PageRef|}}t{{PageRef|}}h{{PageRef|}}e{{PageRef|}} {{PageRef|}}s{{PageRef|}}h{{PageRef|}}o{{PageRef|}}p{{PageRef|}}",
        "Tags": [
            "Wraith",
            "Hero",
            "Shiv",
            "",
            "Ability",
            "Shop"
        ]
    }
]