[
    {
        "Description": "* Weapon tree investment bonus increased by 6-12% (from 6/8/12/18/26/36/52/68/78/88% to 7/9/13/20/29/40/58/72/83/93)",
        "Tags": [
            "Other"
        ]
    },
    {
        "Description": "* Spirit Power scaling globally reduced by -7%",
        "Tags": [
            "Other"
        ]
    },
    {
        "Description": "* {{PageRef|Lady Geist}}: {{PageRef|Malice}} now costs 6% of your Current HP",
        "Tags": [
            "Lady Geist",
            "Hero",
            "Malice",
            "Ability"
        ]
    },
    {
        "Description": "* {{PageRef|Lady Geist}}: {{PageRef|Malice}} damage reduced from 32 to 25",
        "Tags": [
            "Lady Geist",
            "Hero",
            "Malice",
            "Ability"
        ]
    },
    {
        "Description": "* {{PageRef|Lady Geist}}: {{PageRef|Malice}} damage spirit scaling reduced from 0.72 to 0.6",
        "Tags": [
            "Lady Geist",
            "Hero",
            "Malice",
            "Ability"
        ]
    },
    {
        "Description": "* {{PageRef|Lady Geist}}: T2 {{PageRef|Malice}} reduced from 40 to 30",
        "Tags": [
            "Lady Geist",
            "Hero",
            "Malice",
            "Ability"
        ]
    },
    {
        "Description": "* {{PageRef|Shiv}}: {{PageRef|Slice and Dice}} damage reduced from 100 to 80",
        "Tags": [
            "Slice and Dice",
            "Hero",
            "Ability",
            "Shiv"
        ]
    },
    {
        "Description": "* {{PageRef|Shiv}}: Bullet damage growth reduced from 0.246 to 0.22",
        "Tags": [
            "Shiv",
            "Hero"
        ]
    },
    {
        "Description": "* {{PageRef|Vyper}}: {{PageRef|Lethal Venom}} T2 reduced from -60% Healing Reduction to -40%",
        "Tags": [
            "Lethal Venom",
            "Hero",
            "Ability",
            "Vyper"
        ]
    },
    {
        "Description": "* {{PageRef|Vyper}}: {{PageRef|Slither}} T3 reduced from +25% Resist to +20%",
        "Tags": [
            "Slither",
            "Hero",
            "Ability",
            "Vyper"
        ]
    },
    {
        "Description": "* {{PageRef|Pocket}}: {{PageRef|Affliction}} duration reduced from 14s to 12s",
        "Tags": [
            "Affliction",
            "Hero",
            "Ability",
            "Pocket"
        ]
    },
    {
        "Description": "* {{PageRef|Kelvin}} Beam: {{PageRef|Arctic Beam}} DPS reduced from 60 to 50",
        "Tags": [
            "Arctic Beam",
            "Hero",
            "Ability",
            "Kelvin"
        ]
    },
    {
        "Description": "* {{PageRef|Fleetfoot}}: Cooldown reduced from 12s to 11s",
        "Tags": [
            "Fleetfoot",
            "Item",
            "Weapon Item"
        ]
    },
    {
        "Description": "* {{PageRef|Split Shot}}: Shot count increased from 4 to 5",
        "Tags": [
            "Split Shot",
            "Item",
            "Weapon Item"
        ]
    },
    {
        "Description": "* {{PageRef|Active Reload}}: Cooldown reduced from 14s to 12s",
        "Tags": [
            "Active Reload",
            "Item",
            "Weapon Item"
        ]
    },
    {
        "Description": "* {{PageRef|Headhunter}}: Bonus Headshot damage reduced from 150 to 120",
        "Tags": [
            "Headhunter",
            "Item",
            "Weapon Item"
        ]
    },
    {
        "Description": "* {{PageRef|Spirit Rend}}: Cooldown increased from 2s to 2.5s",
        "Tags": [
            "Spirit Rend",
            "Item",
            "Weapon Item"
        ]
    },
    {
        "Description": "* {{PageRef|Cultist Sacrifice}}: Health reduced from 350 to 300",
        "Tags": [
            "Cultist Sacrifice",
            "Item",
            "Weapon Item"
        ]
    },
    {
        "Description": "* {{PageRef|Capacitor}}: Cooldown increased from 30s to 40s",
        "Tags": [
            "Capacitor",
            "Item",
            "Weapon Item"
        ]
    },
    {
        "Description": "* {{PageRef|Divine Barrier}}: Cooldown increased from 36s to 45s",
        "Tags": [
            "Divine Barrier",
            "Item",
            "Vitality Item"
        ]
    },
    {
        "Description": "* {{PageRef|Inhibitor}}: Duration increased from 2.5s to 3s",
        "Tags": [
            "Inhibitor",
            "Item",
            "Vitality Item"
        ]
    },
    {
        "Description": "* Mystic Regen: Duration reduced from 6s to 5s",
        "Tags": [
            "Other"
        ]
    },
    {
        "Description": "* Mystic Regen: Spirit Power scaling reduced from 0.06 to 0.05",
        "Tags": [
            "Other"
        ]
    },
    {
        "Description": "* {{PageRef|Silence Wave}}: Cooldown increased from 24s to 28s",
        "Tags": [
            "Silence Wave",
            "Item",
            "Spirit Item"
        ]
    },
    {
        "Description": "* {{PageRef|Tankbuster}}: Fixed working on mid boss and objectives",
        "Tags": [
            "Tankbuster",
            "Item",
            "Spirit Item"
        ]
    },
    {
        "Description": "* {{PageRef|Decay}}: Spirit power scaling reduced from 0.007 to 0.005",
        "Tags": [
            "Decay",
            "Item",
            "Spirit Item"
        ]
    },
    {
        "Description": "* {{PageRef|Decay}}: Cooldown increased from 22s to 24s",
        "Tags": [
            "Decay",
            "Item",
            "Spirit Item"
        ]
    },
    {
        "Description": "* {{PageRef|Decay}}: Cast range spirit scaling reduced from 0.16 to 0.14",
        "Tags": [
            "Decay",
            "Item",
            "Spirit Item"
        ]
    },
    {
        "Description": "* {{PageRef|Boundless Spirit}}: Heal reduced from 100 to 75",
        "Tags": [
            "Boundless Spirit",
            "Item",
            "Spirit Item"
        ]
    },
    {
        "Description": "* {{PageRef|Mercurial Magnum}}: Fire Rate bonus reduced from +30% to +25%",
        "Tags": [
            "Mercurial Magnum",
            "Item",
            "Spirit Item"
        ]
    },
    {
        "Description": "* {{PageRef|Mercurial Magnum}}: Spirit Power scaling reduced from 0.6 to 0.5",
        "Tags": [
            "Mercurial Magnum",
            "Item",
            "Spirit Item"
        ]
    },
    {
        "Description": "* {{PageRef|Spirit Burn}}: Healing Reduction reduced from -80% to -70%",
        "Tags": [
            "Spirit Burn",
            "Item",
            "Spirit Item"
        ]
    }
]